sgr_commhandler/__init__.py
sgr_commhandler/device_builder.py
sgr_commhandler/api/__init__.py
sgr_commhandler/api/configuration_parameter.py
sgr_commhandler/api/data_point_api.py
sgr_commhandler/api/data_types.py
sgr_commhandler/api/device_api.py
sgr_commhandler/api/functional_profile_api.py
sgr_commhandler/driver/__init__.py
sgr_commhandler/driver/contact/__init__.py
sgr_commhandler/driver/contact/contact_interface_async.py
sgr_commhandler/driver/generic/__init__.py
sgr_commhandler/driver/generic/generic_interface_async.py
sgr_commhandler/driver/messaging/__init__.py
sgr_commhandler/driver/messaging/messaging_interface_async.py
sgr_commhandler/driver/modbus/__init__.py
sgr_commhandler/driver/modbus/modbus_client_async.py
sgr_commhandler/driver/modbus/modbus_interface_async.py
sgr_commhandler/driver/modbus/payload_decoder.py
sgr_commhandler/driver/modbus/shared_client.py
sgr_commhandler/driver/rest/__init__.py
sgr_commhandler/driver/rest/authentication.py
sgr_commhandler/driver/rest/restapi_interface_async.py
sgr_commhandler/utils/__init__.py
sgr_commhandler/utils/value_util.py
sgr_commhandler/validators/__init__.py
sgr_commhandler/validators/resolver.py
sgr_commhandler/validators/validator.py
SGrPythontks4r-0.3.1.dist-info/LICENSE.md
SGrPythontks4r-0.3.1.dist-info/METADATA
SGrPythontks4r-0.3.1.dist-info/WHEEL
SGrPythontks4r-0.3.1.dist-info/top_level.txt
SGrPythontks4r-0.3.1.dist-info/RECORD
