Metadata-Version: 2.1
Name: SGrPythontks4r
Version: 0.3.1
Summary: SmartGridready CommHandler Library
Home-page: https://github.com/SmartGridready/SGrPython#readme
Author: Robin Schoch
Author-email: 
License: BSD
Project-URL: Homepage, https://github.com/SmartGridready/SGrPython
Requires-Python: >=3.9
License-File: LICENSE.md
Requires-Dist: Jinja2<4.0.0,>=3.0.0
Requires-Dist: jmespath<2.0.0,>=1.0.0
Requires-Dist: pymodbus<4.0.0,>=3.0.0
Requires-Dist: setuptools<70.0.0,>=68.0.0
Requires-Dist: xsdata<23.0.0,>=22.0.0
Requires-Dist: xmlschema<4.0.0,>=3.0.0
Requires-Dist: aiohttp<4.0.0,>=3.0.0
Requires-Dist: certifi
Requires-Dist: cachetools<6.0.0,>=5.0.0
Requires-Dist: SGrSpecificationPythontks4r~=2.1
